timetime.py
timetime_demo.py
timetime-1.0.dist-info/METADATA
timetime-1.0.dist-info/WHEEL
timetime-1.0.dist-info/top_level.txt
timetime-1.0.dist-info/RECORD
