Metadata-Version: 2.1
Name: timetime
Version: 1.0
Summary: TimeTime est une classe qui permet d'afficher le temps d'exécution de fonctions, également de les comparer entre eux
Home-page: https://framagit.org/zenjo/timetime/wikis/home
Author: Robert Sebille
Author-email: robert@sebille.name
Maintainer: Robert Sebille
Maintainer-email: robert@sebille.name
License: GNU GPL
Download-URL: https://framagit.org/zenjo/timetime/tree/master
Platform: UNKNOWN
Classifier: Programming Language :: Python :: 3
Classifier: License :: OSI Approved :: GNU General Public License (GPL)
Classifier: Operating System :: OS Independent
